ascii_announcers/__init__.py
ascii_announcers/__main__.py
ascii_announcers/impl.py
ascii_announcers-0.0.2.dist-info/licenses/LICENSE
ascii_announcers-0.0.2.dist-info/METADATA
ascii_announcers-0.0.2.dist-info/WHEEL
ascii_announcers-0.0.2.dist-info/top_level.txt
ascii_announcers-0.0.2.dist-info/RECORD
