Metadata-Version: 2.4
Name: ascii-announcers
Version: 0.0.2
Summary: ASCII announcers for cowsay like announcements
Author-email: wagjo <wagjo@wagjo.com>
License-Expression: MIT
Project-URL: Homepage, https://github.com/wagjo/ascii-announcers
Project-URL: Issues, https://github.com/wagjo/ascii-announcers/issues
License-File: LICENSE
Provides-Extra: deploy
Requires-Dist: twine; extra == "deploy"
Requires-Dist: build; extra == "deploy"
Dynamic: license-file
